{"0": ["Unfortunately, I couldn't find any information on the song"], "1": ["Unfortunately, I couldn't find any information in the provided"], "2": ["The Rolling Stones are from London."], "3": ["Document[4](Title: Bafang Community)"], "4": ["Wawa is a regional convenience store chain, primarily based"], "5": ["I couldn't find any information about the original singer of"], "6": ["It's difficult to pinpoint the exact date of the \""], "7": ["I couldn't find any information about the largest cemetery in"], "8": ["I couldn't find any information on \"Fiddler"], "9": ["MC typically stands for Motorcycle Club."], "10": ["Unfortunately, I couldn't find any information about a movie"], "11": ["The Sound of Music was starred by Julie Andrews"], "12": ["I couldn't find any information about an \"Apple iPhone"], "13": ["I couldn't find any information about a new season of"], "14": ["Unfortunately, the provided documents do not mention the invention of"], "15": ["The National Assembly marked its start in Versailles"], "16": ["I couldn't find any information on the US having a"], "17": ["I couldn't find any information on the Premier League or"], "18": ["I couldn't find any information about an actor named \""], "19": ["I couldn't find any information about the programmer of the"], "20": ["Unfortunately, I couldn't find any information about a TV"], "21": ["The highest peak of southern India is Anamudi,"], "22": ["The Kentucky Wildcats beat Kansas in the 2012 NCAA"], "23": ["I couldn't find any information about a song called \""], "24": ["It was not in any of the given documents."], "25": ["I couldn't find any information on a movie or show"], "26": ["Unfortunately, I couldn't find any information about the phrase \""], "27": ["Unfortunately, I couldn't find any information on the Cleveland"], "28": ["I couldn't find any information about a person named J"], "29": ["I couldn't find any information about a \"Jw"], "30": ["Quimby"], "31": ["I couldn't find any information about a \"Hall of"], "32": ["San Angelo is located in West Texas."], "33": ["No information found on the music for \"The Sorcerer"], "34": ["CVS Pharmacy"], "35": ["The United States abandoned the gold standard in 1971"], "36": ["Bill Murray"], "37": ["Hallmark Movies & Mysteries is on Hallmark Channel"], "38": ["Unfortunately, I couldn't find any information about performers at"], "39": ["I couldn't find any information on \"Robbie Douglas"], "40": ["I couldn't find any information that suggests \"Close Enc"], "41": ["Unfortunately, I couldn't find any information about a character"], "42": ["I couldn't find any information on a TV show or"], "43": ["Unfortunately, I couldn't find any information on the number"], "44": ["The southernmost part of Canada is Newfoundland."], "45": ["I couldn't find any information about a song called \""], "46": ["I couldn't find any information on who wrote the score"], "47": ["According to available information, I couldn't find any direct"], "48": ["Self-awareness"], "49": ["Rothschild"], "50": ["A quintuplets"], "51": ["No information about a TV show called \"Season 5"], "52": ["Unfortunately, I couldn't find any information about a song"], "53": ["I couldn't find any information on a character named \""], "54": ["Lowering price below cost."], "55": ["I couldn't find any information about a new season of"], "56": ["None of the provided documents mention MLB or World Series wins"], "57": ["I couldn't find any information about the number of clean"], "58": ["I couldn't find any information about the current Chief of"], "59": ["I couldn't find any information on the movie \"A"], "60": ["Unfortunately, I couldn't find any information about a TV"], "61": ["I couldn't find any information about a movie called \""], "62": ["I couldn't find any information on \"the others\""], "63": ["I couldn't find any information that suggests a specific team"], "64": ["I couldn't find any information about a \"Garden"], "65": ["Badminton originated from a game called 'Poona"], "66": ["I couldn't find any information about a movie or book"], "67": ["Unfortunately, the provided documents don't seem to be relevant"], "68": ["Unfortunately, the provided documents do not mention anything about tire"], "69": ["Gurbhagat Singh"], "70": ["I couldn't find any information on a band called \""], "71": ["Liberia is classified as an African country, specifically"], "72": ["I couldn't find any information about a person named \""], "73": ["I couldn't find any information about the theme song for"], "74": ["I couldn't find any information on a song with the"], "75": ["I couldn't find any information about a movie \"B"], "76": ["The Gorillaz do not have a song called \""], "77": ["Document[1](Title: The Emperor's New Gro"], "78": ["I couldn't find any information about a \"lane\""], "79": ["Unfortunately, I couldn't find any information about \"Ru"], "80": ["I couldn't find any information about recent Stanley Cup Finals"], "81": ["I couldn't find any information on a TV show called"], "82": ["Julius Caesar"], "83": ["The vestibular system."], "84": ["Samuel Morse"], "85": ["Unfortunately, I couldn't find any information on Wales winning"], "86": ["Unfortunately, I couldn't find any information that directly relates"], "87": ["Unfortunately, I couldn't find any information on a film"], "88": ["Unfortunately, I couldn't find any information on a song"], "89": ["Unfortunately, I couldn't find any information on a World"], "90": ["Unfortunately, I couldn't find any information about Luann"], "91": ["There is no information about the number of episodes in Season"], "92": ["I couldn't find any information on the number of Raj"], "93": ["I couldn't find any information about a character named Bill"], "94": ["I couldn't find any information about \"Ink Master"], "95": ["I couldn't find any information about \"Pure Prairie League"], "96": ["I couldn't find any information on a \"path train"], "97": ["The answer is not explicitly mentioned in the provided documents."], "98": ["I couldn't find any information about \"Challenge champs vs"], "99": ["The idea of representative government first developed in ancient Greece,"], "100": ["Chuck Berry"], "101": ["According to historical records, slavery was abolished in the United"], "102": ["Unfortunately, I couldn't find any information about the San"], "103": ["Unfortunately, I couldn't find any information on a song"], "104": ["The bulls run in Pamplona during the San Ferm"], "105": ["Robert Edmund Strahorn"], "106": ["I couldn't find any information about the winner of Britain"], "107": ["Unfortunately, I couldn't find any information on the Og"], "108": ["I couldn't find any information about \"Call of Duty"], "109": ["Unfortunately, the provided documents do not seem to be relevant"], "110": ["Unfortunately, I couldn't find any information on a well"], "111": ["The OSI layer that defines the signal rates and voltages"], "112": ["I couldn't find any information about the GOP taking control"], "113": ["Arsenic"], "114": ["I couldn't find any information on \"Season 5"], "115": ["A bird that can't fly is called a ground bird"], "116": ["By the mid-1930s, the most influential"], "117": ["Pakistan"], "118": ["Unfortunately, I couldn't find any information about the song"], "119": ["Linnaeus"], "120": ["Jack Fingleton"], "121": ["There is no mention of a \"gum wall\""], "122": ["April 22, 1963"], "123": ["Independence Hall."], "124": ["1941"], "125": ["I couldn't find any information on a movie or show"], "126": ["Leather"], "127": ["According to the available documents, I couldn't find any"], "128": ["I couldn't find any information about a bond formed in"], "129": ["Unfortunately, I couldn't find any information on a person"], "130": ["Laura Prepon"], "131": ["The Renaissance period (14th-17th centuries)."], "132": ["I couldn't find any information on \"Asia's Next"], "133": ["The Magna Carta was signed in 1215"], "134": ["Unfortunately, I couldn't find any information on the origin"], "135": ["I couldn't find any information on a specific game between"], "136": ["Unfortunately, I couldn't find any information on a show"], "137": ["It is not possible to answer this question as there is"], "138": ["Frontal lobe"], "139": ["Paul, Michael and Neil (Paul McCartney, Michael C"], "140": ["I couldn't find any information that directly links to a"], "141": ["According to popular culture, \"Simple Simon\" is believed"], "142": ["WLS-TV"], "143": ["I couldn't find any information on a weather channel on"], "144": ["Galadriel"], "145": ["Unfortunately, I couldn't find any information on the names"], "146": ["DCA stands for Denver Colorado Airport."], "147": ["I couldn't find any information about a 2011"], "148": ["I couldn't find any information about a song called \""], "149": ["The answer is not explicitly mentioned in the provided documents."], "150": ["I couldn't find any information about a person named Pop"], "151": ["The Kansas City style of jazz arrangements were based on blues"], "152": ["Jack Norworth"], "153": ["Peristalsis."], "154": ["Unfortunately, the provided documents do not seem to be related"], "155": ["Monarch butterflies migrate to Mexico"], "156": ["The answer is not available in the provided documents."], "157": ["I couldn't find any information on who plays the queen"], "158": ["Neal butt"], "159": ["I couldn't find any information on when Tasmania was cut"], "160": ["The structures of the nephron where filtration occurs are:\n\n"], "161": ["Orlando"], "162": ["I couldn't find any information about the \"Federal Bureau"], "163": ["I cannot provide information about a specific individual's age,"], "164": ["Unfortunately, I couldn't find any information about a movie"], "165": ["Unfortunately, I couldn't find any information about the administration"], "166": ["The origin of the phrase \"Keep Calm and Carry"], "167": ["I couldn't find any information about the world's largest"], "168": ["Maureen McCormick"], "169": ["I couldn't find any information about a \"Liberty"], "170": ["I couldn't find any information on \"Nevada"], "171": ["The Adventures of Tom Sawyer was first published in 187"], "172": ["I couldn't find any information on a \"Commod"], "173": ["I couldn't find any information about a song called \""], "174": ["Unfortunately, I couldn't find any information about a person"], "175": ["Here is a 5-token answer:\n\nEthiopia"], "176": ["I couldn't find any information about a dog named Charlie"], "177": ["There is no information about a rugby world cup final in"], "178": ["I couldn't find any information about \"The Wonders"], "179": ["The UK is a state."], "180": ["Unfortunately, the provided documents do not mention the British Open"], "181": ["Laura Prepon"], "182": ["Unfortunately, none of the provided documents mention the introduction of"], "183": ["I couldn't find any information about a competition or show"], "184": ["The answer is \"Thomas Jefferson\""], "185": ["USA has not won the Gold Cup recently, but the"], "186": ["I couldn't find any information on when \"Orange is"], "187": ["I couldn't find any information on \"Season 3"], "188": ["Lucky charm"], "189": ["Unfortunately, I couldn't find any information about the tallest"], "190": ["Unfortunately, none of the provided documents mention the Middle Eastern"], "191": ["According to various sources, the main characters in the TV"], "192": ["The 5th letter of the Greek alphabet is \""], "193": ["It is used to explain price competition in oligopolies"], "194": ["I couldn't find any information on \"Everybody Loves Raymond"], "195": ["I couldn't find any information on \"Season 3"], "196": ["There is no information in the provided documents that relates to"], "197": ["Madhusudan Mistry"], "198": ["Unfortunately, I couldn't find any information about the Le"], "199": ["I don't have any information about the current or recent"], "200": ["Unfortunately, I couldn't find any information on a song"], "201": ["Marcel"], "202": ["Typically 4 years."], "203": ["The 4 cultures that make up the Hellenistic"], "204": ["The rank after Captain in the Air Force is Major."], "205": ["I couldn't find any information about a TV show called"], "206": ["I couldn't find any information on a \"Swar"], "207": ["I couldn't find any information about a character named \""], "208": ["Charles Dickens wrote Oliver Twist, however the actor who portrayed"], "209": ["Guns N' Roses"], "210": ["Benjamin Franklin"], "211": ["According to the US Constitution, all bills must originate in"], "212": ["The Paris Agreement was signed by 196 countries."], "213": ["Pax Romana refers to the period of relative peace"], "214": ["Kevin Feely"], "215": ["Answer: 16"], "216": ["I couldn't find any information about Serena and Nate's"], "217": ["A covalent bond."], "218": ["I couldn't find any information about South Korea separating from"], "219": ["Based on the provided documents, I couldn't find a"], "220": ["There is no information about the current English royal family in"], "221": ["Alan Rickman"], "222": ["I couldn't find any information about the tallest tower in"], "223": ["Subsidies can come from various sources, but generally"], "224": ["I couldn't find any information on a song called \""], "225": ["I couldn't find any information about \"Wayne's"], "226": ["I couldn't find any information on Steph Curry's playing"], "227": ["Unfortunately, I couldn't find any information about the specific"], "228": ["Will Smith"], "229": ["WVPT"], "230": ["Cell division"], "231": ["Clostridium tetani is typically found in the"], "232": ["I couldn't find any information on \"Bendy"], "233": ["I couldn't find any information about a \"subway"], "234": ["The Handmaid's Tale has a total of 5"], "235": ["George Herbert Mead"], "236": ["The record for most strikeouts in a season by a hitter"], "237": ["I couldn't find any information about F1 races or"], "238": ["The hepatic portal vein carries blood from the gastrointestinal tract"], "239": ["I couldn't find any information about Harley Quinn's first"], "240": ["Al Capone"], "241": ["Here is the answer in 5 tokens:\n\nThe War"], "242": ["In North Dakota, it normally snows from October to"], "243": ["I couldn't find any information on who has won the"], "244": ["The United States declared independence from Great Britain."], "245": ["I couldn't find any information about Boku no Hero"], "246": ["I couldn't find any information about Beyonc\u00e9 performing at"], "247": ["I couldn't find any information on the current or past"], "248": ["Unfortunately, the provided documents don't seem to have any"], "249": ["I couldn't find any information about a movie called \""], "250": ["Unfortunately, I couldn't find any information on a "], "251": ["homogeneous"], "252": ["I couldn't find any information about \"Cheaper by"], "253": ["Unfortunately, the provided documents do not mention the three measurements"], "254": ["The Tasman Sea"], "255": ["I couldn't find any information about a movie or TV"], "256": ["I couldn't find any information on \"Steven Universe\""], "257": ["Unfortunately, I couldn't find any information about Jeep making"], "258": ["I couldn't find any information about a person named Michael"], "259": ["Unfortunately, I couldn't find any information about the song"], "260": ["The 5 major circles of latitude are: \n1"], "261": ["I couldn't find any information about \"The Good Fight"], "262": ["The Scarecrow"], "263": ["The origin of the term \"helter skelter\""], "264": ["There is no information about \"com2 port\" in"], "265": ["I couldn't find any information about a \"Knight's"], "266": ["I couldn't find any information about the fastest roller coaster"], "267": ["I couldn't find any information about a person named Marty"], "268": ["Guglielmo Marconi"], "269": ["Our Girl has 3 episodes in Season 2."], "270": ["Bottleneck effect."], "271": ["The main diamond cutting centre in India is Surat"], "272": ["The Bhagavad Gita has 18 chapters."], "273": ["I couldn't find any information about the New York Mets"], "274": ["Unfortunately, I couldn't find any specific information in the"], "275": ["Unfortunately, I couldn't find any information about a well"], "276": ["The Prestige (2006)"], "277": ["I couldn't find any information on the Carolina Hurricanes'"], "278": ["I couldn't find any information on \"lane splitting\""], "279": ["I couldn't find any information on a TV show called"], "280": ["I couldn't find any information about \"The Lion King"], "281": ["Brazil was the runner-up."], "282": ["The majority of the mass of an atom is found in"], "283": ["The answer is HIV."], "284": ["The first national draft, also known as the \"White"], "285": ["I couldn't find any information on a specific episode of"], "286": ["I couldn't find any information on the CFL (Canadian"], "287": ["I couldn't find any information on a movie or TV"], "288": ["I couldn't find any information about someone singing \"R"], "289": ["Don't have information on \"Long Cool Woman in a"], "290": ["Unfortunately, I couldn't find any information on the number"], "291": ["I couldn't find any information about a specific person named"], "292": ["I couldn't find any information on a TV show called"], "293": ["I couldn't find any information on a specific event of"], "294": ["I couldn't find any information about \"Sa Re Ga"], "295": ["I couldn't find any information on the question \"who"], "296": ["Unfortunately, I couldn't find any information about a character"], "297": ["1"], "298": ["The feature of earth's movement that takes about 26"], "299": ["I couldn't find any information about a bird with a"], "300": ["Unfortunately, I couldn't find any information about who wrote"], "301": ["I couldn't find any information about a character named Spencer"], "302": ["I couldn't find any information on a \"Madam"], "303": ["Proxy"], "304": ["I couldn't find any information on \"Fear the Walking"], "305": ["I couldn't find any information on a person named Scott"], "306": ["Ferdinand Magellan"], "307": ["I couldn't find any information about dams on the Missouri"], "308": ["I couldn't find any information on a character named \"Neil"], "309": ["Unfortunately, I couldn't find any information about \"Chron"], "310": ["The Deepwater Horizon oil spill, caused by BP,"], "311": ["The first submarine used in war was the American Turtle,"], "312": ["I didn't catch what you said."], "313": ["1948"], "314": ["Charles Darwin"], "315": ["Real Madrid"], "316": ["Andrew H. Burke"], "317": ["Sorry, no information about \"The Amazing Spiderman "], "318": ["Most currency is printed by central banks, such as the"], "319": ["George Michael"], "320": ["The answer is:  John Hodge"], "321": ["Unfortunately, I don't have information about any recent announcements or"], "322": ["The longest bone in the body is the femur,"], "323": ["I couldn't find any information about an actress named \""], "324": ["I couldn't find any information about an \"X-Men"], "325": ["The song \"Don't Change\" by INXS was"], "326": ["I couldn't find any information about the first cricket match"], "327": ["Jesus Christ"], "328": ["Unfortunately, I couldn't find any information about a song"], "329": ["Aadhaar cards are used for various purposes in India"], "330": ["Unfortunately, the provided documents do not mention the Imperial City in"], "331": ["The answer is Robert Malthus"], "332": ["10"], "333": ["The Federal Deposit Insurance Corporation (FDIC) was intended"], "334": ["I couldn't find any information about a \"My Little"], "335": ["Patrick Swayze"], "336": ["Voni Morrison"], "337": ["According to various sources, cell phones became common in the"], "338": ["Savannas."], "339": ["There is no mention of a book called \"Waiting for"], "340": ["The answer is: John Goode"], "341": ["The Third Party System took place in American politics from approximately"], "342": ["St. Patrick"], "343": ["I couldn't find any information on a film or TV"], "344": ["There is no mention of the surname \"Johnston\""], "345": ["The largest meteorite ever found on Earth, the V"], "346": ["Troy Barker"], "347": ["Most of our electricity comes from fossil fuels (coal,"], "348": ["The 8-track tape was introduced in 1964"], "349": ["I couldn't find any information on the winner of the"], "350": ["I couldn't find any information on \"The Haves"], "351": ["I couldn't find any information on a coach with the"], "352": ["Conquistadors went to the Americas."], "353": ["I couldn't find any information about \"King Kong\""], "354": ["I couldn't find any information about a \"Defender"], "355": ["I couldn't find any information on Season 14 of"], "356": ["I couldn't find any information on the longest canal tunnel"], "357": ["Light Yagami"], "358": ["The Ohio Valley was situated between lands claimed by Great Britain"], "359": ["Unfortunately, none of the provided documents seem to mention the"], "360": ["Answer: 10"], "361": ["Unfortunately, I couldn't find any information about \"Call"], "362": ["The answer is Robert Hu\u0308bner"], "363": ["Three-star major"], "364": ["There is no information about Bruce Wayne or a person coming"], "365": ["I couldn't find any information on a book entitled \""], "366": ["I couldn't find any information about Canada's participation in"], "367": ["I couldn't find any information about Mandy Moore playing"], "368": ["The Mockingjay, the protagonist of The Hunger Games"], "369": ["Unfortunately, I couldn't find any information on the meaning"], "370": ["The financial crisis started in 2007, not "], "371": ["Welding"], "372": ["I couldn't find any information about a \"Flushing"], "373": ["Unfortunately, I couldn't find any information about the French"], "374": ["Ancient Greece is often considered the start of Western civilization"], "375": ["Unfortunately, I couldn't find any information about a person"], "376": ["Neither, Ferris wheels and teddy bears are modern"], "377": ["Poverty, famine, and British rule."], "378": ["I couldn't find any information on \"Troll Hunters"], "379": ["Unfortunately, the provided documents do not mention the state court"], "380": ["I couldn't find any information on a person or a character"], "381": ["I couldn't find any information about Cuba gaining independence from"], "382": ["The volcano that erupted at Mt. St. Helens"], "383": ["Estrogen levels peak around ovulation, typically midway through"], "384": ["Crohn's disease."], "385": ["The Olsen twins, Mary-Kate and Ashley Olsen,"], "386": ["Sidney Carr Mize"], "387": ["1950"], "388": ["South Korea."], "389": ["I couldn't find any information about a character named \""], "390": ["GPS became available for civilian use in 1989"], "391": ["The answer is the Houston Rockets"], "392": ["The answer is not found in the provided documents."], "393": ["I couldn't find any information about the mayor of Detroit"], "394": ["I couldn't find any information on England reaching the semif"], "395": ["I couldn't find any information about Count Basie playing"], "396": ["I couldn't find any information on \"Mabel\""], "397": ["I couldn't find any information on a movie called \""], "398": ["Unfortunately, I couldn't find any information on the Erie"], "399": ["None of the given documents"], "400": ["I couldn't find any information about the \"First North"], "401": ["Unfortunately, I couldn't find any information about \"Grace"], "402": ["I couldn't find any information about a \"French drop"], "403": ["I couldn't find any information on a person named Stacey"], "404": ["Unfortunately, I couldn't find any information about a movie"], "405": ["The voices of Hammy, Verne, and O"], "406": ["Unfortunately, the given documents don't seem to contain the"], "407": ["Popeye's nephews were Olive's brothers,"], "408": ["The strongest bone in the body is the femur ("], "409": ["I couldn't find any information about the Lakers being in"], "410": ["Panama."], "411": ["I couldn't find any information about a person named Cindy"], "412": ["Charlie Sheen"], "413": ["17"], "414": ["I couldn't find any information about the construction of the"], "415": ["Unfortunately, I couldn't find any information about a movie"], "416": ["I couldn't find any information about the New York Rangers"], "417": ["Meter."], "418": ["I couldn't find any information in the given documents about"], "419": ["I couldn't find any information about the Houston Astros changing"], "420": ["Imran Khan"], "421": ["No information about Elton John writing a song for Marilyn"], "422": ["University of North Carolina"], "423": ["The necessary element is \"water\""], "424": ["Unfortunately, the provided documents do not mention the invention of"], "425": ["The name \"Hamza\" in Arabic means \"strong"], "426": ["Around 10,000 years ago."], "427": ["I couldn't find any information about the Dodgers moving to"], "428": ["I couldn't find any information about the number of ships"], "429": ["I couldn't find any information about a song with the"], "430": ["I couldn't find any information about Hansel and Gret"], "431": ["Unfortunately, I couldn't find any information on \"P"], "432": ["There is no information about the Pacific Ocean or its deepest"], "433": ["Drooling excessively can be a sign of anxiety or"], "434": ["Isaac Newton"], "435": ["Unfortunately, I couldn't find any information in the provided"], "436": ["Unfortunately, I couldn't find any information on \"All"], "437": ["Hayden Christensen"], "438": ["Tyrion's trial"], "439": ["Primary hemostasis"], "440": ["Unfortunately, I couldn't find any information on the specific"], "441": ["I couldn't find any information about the Australian Open winners"], "442": ["The fourth letter of the Greek alphabet is Delta (\u0394"], "443": ["Johnny Depp"], "444": ["I couldn't find any information about the two most successful"], "445": ["I couldn't find any information on the music for \""], "446": ["Robert E. Lee"], "447": ["I couldn't find any information on a TV show called"], "448": ["I couldn't find any information about a \"youngest"], "449": ["Cumulonimbus"], "450": ["I couldn't find any information about \"The Carrie Di"], "451": ["Unfortunately, I couldn't find any information about who sings"], "452": ["The Great Wall of China was not built by the Saf"], "453": ["The British Virgin Islands belong to the United Kingdom."], "454": ["There is no information about the TV show \"Being Mary"], "455": ["Chubby Checker"], "456": ["There is no mention of a \"hinge joint\""], "457": ["Unfortunately, none of the provided documents seem to mention the"], "458": ["Unfortunately, I couldn't find any information about France arriving"], "459": ["Unfortunately, I couldn't find any information on a TV"], "460": ["Unfortunately, none of the provided documents contain information on the"], "461": ["I couldn't find any information on a song called \""], "462": ["I couldn't find any information that matches the description \""], "463": ["I couldn't find any information about a 3-point"], "464": ["The heat in chillies comes from capsaicin"], "465": ["Unfortunately, I couldn't find any information about the first"], "466": ["Resident Evil 7 has a first-person perspective,"], "467": ["I couldn't find any information about a song called \""], "468": ["I couldn't find any information on a song titled \""], "469": ["The Navajo code talkers worked for the US"], "470": ["According to historical records, Canaan was named after the"], "471": ["Unfortunately, I couldn't find any information on the person"], "472": ["The answer is not explicitly mentioned in the provided documents."], "473": ["I couldn't find any information on \"You've Got"], "474": ["Gordon Ramsay"], "475": ["Georges Clemenceau"], "476": ["I couldn't find any information about a character named \""], "477": ["Macy's was founded by Rowland H. Macy"], "478": ["There is no information about a \"Season 5 of"], "479": ["I couldn't find any information on \"The Real House"], "480": ["That information is not available in the provided documents."], "481": ["I couldn't find any information on a \"Wildlife"], "482": ["Paul Hollywood"], "483": ["Manifest Destiny"], "484": ["Millie Bobby Brown"], "485": ["Pharrell Williams"], "486": ["Sorry, I do not have any information on whose voice is"], "487": ["The answer cannot be deduced from the provided documents."], "488": ["I couldn't find any information about a Heisman Trophy"], "489": ["The Great Salt Lake"], "490": ["I couldn't find any information about the Senior Bowl being"], "491": ["Unfortunately, I couldn't find any information about a \""], "492": ["I couldn't find any information on the person who plays"], "493": ["I couldn't find any information on who sang \"to"], "494": ["You can get a Norwegian Forest cat from a breeder"], "495": ["I couldn't find any information about a specific Lauryn"], "496": ["I couldn't find any information about a person's runs"], "497": ["The Little Mermaid, the Disney movie, takes place"], "498": ["The plasma membrane."], "499": ["I couldn't find any information on the origin of the"], "500": ["Ritchie Valens"], "501": ["Bartow-Pell Mansion"], "502": ["1954"], "503": ["Unfortunately, I couldn't find any information about a song"], "504": ["Montepulciano d'Abruzzo"], "505": ["Thomas More"], "506": ["Thursday"], "507": ["To change a lead atom into a gold atom, nuclear"], "508": ["I couldn't find any information on a character named \""], "509": ["I couldn't find any information on an actor playing a"], "510": ["The music for \"The Rocky Horror Picture Show\" was"], "511": ["I couldn't find any information on \"Our Miss Brooks"], "512": ["I couldn't find any information about a kid who plays"], "513": ["I couldn't find any information about a person playing the"], "514": ["Christopher Lloyd"], "515": ["Thomas Edison"], "516": ["I couldn't find any information about Sherlock Holmes working as"], "517": ["I couldn't find any information on \"America's Got"], "518": ["There is no information about a seismograph being invented"], "519": ["I couldn't find any information about the song \"You"], "520": ["A stone or calculus in the nose is called a nasal"], "521": ["I couldn't find any information on the current Prime Minister"], "522": ["I couldn't find any information about a \"New World"], "523": ["There is no information about a football player named Fernando Torres"], "524": ["I couldn't find any information on a person named Whites"], "525": ["There is no mention of a character named \"they\""], "526": ["I couldn't find any information on a song with the"], "527": ["No information found about \"Meredith Quill\""], "528": ["The Clean Air Act of 1970 was written by"], "529": ["I could not find any information on a Garfield comic"], "530": ["I couldn't find any information about someone scoring for Southampton"], "531": ["The part of the brain that controls speech is the Bro"], "532": ["Unfortunately, the provided documents do not mention the author of"], "533": ["Idaho"], "534": ["There is no information about a movie called \"Willy"], "535": ["Small intestine."], "536": ["I couldn't find any information about the USA beating Mexico"], "537": ["Unfortunately, there is no information about a \"Declaration of"], "538": ["I couldn't find any information about \"Harry Potter:"], "539": ["The last Western Roman Emperor, Romulus Augustus,"], "540": ["The Monroe Doctrine."], "541": ["No information is found in the provided documents about a stadium"], "542": ["The origin of the first mammal is not precisely dated"], "543": ["I couldn't find any information about Angela having a baby on"], "544": ["I couldn't find any information about \"Vinnie\""], "545": ["I couldn't find any information about a movie called \""], "546": ["I couldn't find any information about the first Krispy"], "547": ["Individuals"], "548": ["The film \"The Quiet Man\" (not \"The"], "549": ["According to the provided documents, I was unable to find"], "550": ["Unfortunately, I couldn't find any information that directly attributes"], "551": ["The process of removing an element from a stack is called"], "552": ["Unfortunately, I couldn't find any information on a school"], "553": ["I couldn't find any information about a golf tournament in"], "554": ["The original Three Stooges (Moe Howard,"], "555": ["I couldn't find any information on \"Gwen\""], "556": ["I couldn't find any information on the number of FIFA"], "557": ["New York"], "558": ["Unfortunately, I couldn't find any information on a Batman"], "559": ["I couldn't find any information on \"The Suite Life"], "560": ["Prokaryotic"], "561": ["France became a republic in 1792, after the"], "562": ["Haddonfield"], "563": ["Unfortunately, I couldn't find any information about the song"], "564": ["Unfortunately, I couldn't find any information about the song"], "565": ["Energy and heat"], "566": ["I couldn't find any information on the phrase \"I"], "567": ["I couldn't find any information on a specific \"new"], "568": ["The Boston Red Sox"], "569": ["The answer is: \"My Songs Know What You Did"], "570": ["Unfortunately, I couldn't find any information about the iPad"], "571": ["I couldn't find any information about Arches National Park"], "572": ["I couldn't find any information on the song \"You"], "573": ["I couldn't find any information on a person named Prem"], "574": ["I couldn't find any information about the main character in"], "575": ["I couldn't find any information about a character getting pregnant"], "576": ["I couldn't find any information on \"the Knicks\""], "577": ["I couldn't find any information on a song called \""], "578": ["I couldn't find any information on an actress named Abby"], "579": ["Unfortunately, the provided documents do not seem to be relevant"], "580": ["I couldn't find any information on a person with the"], "581": ["I couldn't find any information about a movie that has"], "582": ["According to moral and ethical principles, Hare's two"], "583": ["The French Revolution's significance lies in shaping modern democracy,"], "584": ["I couldn't find any information on Nigeria becoming a colony"], "585": ["2007"], "586": ["I couldn't find any information about Meredith and Derek getting"], "587": ["I couldn't find any information about a \"new tax"], "588": ["I couldn't find any information about the song \"Just"], "589": ["Unfortunately, I couldn't find any information on \"China"], "590": ["Winston Churchill"], "591": ["Light."], "592": ["I couldn't find any information about a person named \""], "593": ["I couldn't find any information on an Ariana Grande"], "594": ["Dwight Moody"], "595": ["Unfortunately, I couldn't find any information about the Los"], "596": ["There is no information about NFL teams or games in the"], "597": ["I couldn't find any information about the last time the"], "598": ["I couldn't find any information about the release date of"], "599": ["I couldn't find any information on a song called \""], "600": ["\"Germs, Guns, and Steel\" is a"], "601": ["Unfortunately, none of the provided documents seem to be related"], "602": ["I couldn't find a match in the provided documents for"], "603": ["I couldn't find any information about the first Buc"], "604": ["1. 1.4 \u00c5"], "605": ["I couldn't find any information about a specific \"Beauty"], "606": ["Mouth lining"], "607": ["Captain Clifton C. Williams"], "608": ["Touchback in NFL occurs when the ball is placed at"], "609": ["The preamble of the Indian Constitution has been amended 64"], "610": ["Architect"], "611": ["Unfortunately, I couldn't find any information about a \""], "612": ["I couldn't find any information on a \"First S"], "613": ["There is no information about the FIFA World Cup 2018"], "614": ["Francis Scott Key"], "615": ["I couldn't find any information on \"dehradh"], "616": ["I couldn't find any information about a song called \""], "617": ["The auditory canal is formed out of the temporal bone."], "618": ["I couldn't find any information about a Winnie the"], "619": ["According to my knowledge, Bowen-Campbell House doesn"], "620": ["I couldn't find any information about a TV show called"], "621": ["Some examples of words that are pronounced the same in English"], "622": ["In North Carolina, fall typically starts around late September to"], "623": ["Investment"], "624": ["The monarchs lived at St. James's Palace before"], "625": ["The acrosome is a cap-like structure on the"], "626": ["The phrase \"something old, something new, something borrowed"], "627": ["Oliver Twist is apprenticed to Mr. Brownlow"], "628": ["Starch granules serve as energy storage units, acting"], "629": ["The US"], "630": ["Music originated around 4000 BC."], "631": ["According to various sources, in the Science Olympiad,"], "632": ["I couldn't find any information on \"May the bird"], "633": ["Selena Gomez"], "634": ["Unfortunately, I couldn't find any information about the creation"], "635": ["uterus"], "636": ["The Duffer Brothers' hometown of Durham, North Carolina"], "637": ["Unfortunately, I couldn't find any information about a TV"], "638": ["I couldn't find any information about Billy Russo becoming a"], "639": ["Unfortunately, I couldn't find any information about a person"], "640": ["Dean Martin"], "641": ["I couldn't find any information about a theme song for"], "642": ["I couldn't find any information about a specific stadium called"], "643": ["I couldn't find any information about a specific \"201"], "644": ["Not enough information is provided in the given documents to accurately"], "645": ["I couldn't find any information about a movie or release"], "646": ["Unfortunately, I couldn't find any information about a person"], "647": ["I couldn't find any information on a person named Kim"], "648": ["The first Star Trek movie, \"Star Trek: The"], "649": ["I couldn't find any information on a specific release date"], "650": ["No information available."], "651": ["Unfortunately, I couldn't find any information about \"L"], "652": ["I couldn't find any information on the time it takes"], "653": ["Approximately 21%"], "654": ["Unfortunately, I couldn't find any information about the Smithsonian"], "655": ["The US troops started fighting in Vietnam in 1965"], "656": ["Unfortunately, I couldn't find any information on a person"], "657": ["Duke"], "658": ["Document[6](Title: Haldimand Pro"], "659": ["I couldn't find any information on \"I Wish It"], "660": ["The Maratha Confederacy was defeated by the British in"], "661": ["The first non-aligned summit took place in Belgrade,"], "662": ["Unfortunately, I couldn't find any information about \"The"], "663": ["I couldn't find any information about a president of Poland"], "664": ["You vomit food back up."], "665": ["I couldn't find any information on a character named Ruth"], "666": ["\"Cake by the Ocean\" is by DNCE"], "667": ["I couldn't find any information on a person being referred"], "668": ["I couldn't find any information about \"The Little R"], "669": ["The Tin Man is a character in the Wizard of Oz"], "670": ["I couldn't find any information on the newest Royal Caribbean"], "671": ["Franklin D. Roosevelt"], "672": ["I couldn't find any information about the football transfer window"], "673": ["Three's Company was primarily filmed in Los Angeles, California"], "674": ["Dinah Washington"], "675": ["There is no information about a person named Charlie writing \""], "676": ["I couldn't find any information about a university named \""], "677": ["I couldn't find any information on \"What a Feeling"], "678": ["I couldn't find any information about Sampath Bank in"], "679": ["I couldn't find any information about \"Season 3"], "680": ["There is no information available about who was sailing the Titanic"], "681": ["I couldn't find any information on \"Cavs\""], "682": ["I couldn't find any information on \"Jessica Jones\""], "683": ["The first cassette tape, the tape recorder, was invented"], "684": ["The Wicked Witch of the West"], "685": ["I couldn't find any information on a specific personality being"], "686": ["David Cassidy"], "687": ["Wedding parties"], "688": ["American Horror Story Season 1 has 12 episodes."], "689": ["I couldn't find any information on who has held the"], "690": ["The sway bar is typically located near the front and rear"], "691": ["Apple"], "692": ["I couldn't find any information about a film called \""], "693": ["2006"], "694": ["I couldn't find any information about a character named \"son"], "695": ["I couldn't find any information about the Mongols ruling"], "696": ["I couldn't find any information on Teddy Altman's"], "697": ["I was unable to find any information about a team called"], "698": ["According to the Bible, Cain and Abel were two brothers"], "699": ["I couldn't find any information about a comedian saying \""], "700": ["I couldn't find any information about a person named Eric"], "701": ["I couldn't find any information about GTA 5 having"], "702": ["Unfortunately, the provided documents do not contain information about UNESCO"], "703": ["I couldn't find any information that suggests a specific actor"], "704": ["The Himalayan mountains represent a convergent plate boundary."], "705": ["Common law."], "706": ["Unfortunately, I couldn't find any information on \"New"], "707": ["Unfortunately, I couldn't find any information on a character"], "708": ["The Canadian Radio-television and Telecommunications Commission (C"], "709": ["No information is found in the given documents about the Universal"], "710": ["I couldn't find any information on the latest version of"], "711": ["Crispin Glover"], "712": ["The Epic of Gilgamesh ( oldest surviving work of"], "713": ["The function of the proteins secreted by cells of the"], "714": ["I couldn't find any information on who has sung the"], "715": ["I couldn't find any information about \"Master Chef Junior"], "716": ["There is no information about an extra bank holiday in the"], "717": ["I couldn't find any information on a Pok\u00e9mon release date"], "718": ["Loryn"], "719": ["Spain"], "720": ["I couldn't find any information about a song called \""], "721": ["I couldn't find any information about a character named \""], "722": ["approximately 240 miles"], "723": ["Carbon dioxide"], "724": ["I couldn't find any information about Freddie Highmore playing"], "725": ["I couldn't find any information about \"The Fast and"], "726": ["I couldn't find any information about \"Jurassic World"], "727": ["I couldn't find any information about Sonic commercials featuring "], "728": ["I couldn't find any information linking \"Invasion\""], "729": ["The answer is Joe Pantoliano"], "730": ["Unfortunately, I couldn't find any information on \"Mc"], "731": ["No"], "732": ["I couldn't find any information about a character named Neil"], "733": ["Claude Rains"], "734": ["I couldn't find any information about a person named Violet"], "735": ["The \"Clickers\""], "736": ["Unfortunately, I couldn't find any information about a \""], "737": ["I couldn't find any information about the \"Kim family"], "738": ["It seems the answer might be not found in the provided"], "739": ["I couldn't find any information about \"D1 college"], "740": ["I couldn't find any information about a \"People's"], "741": ["Unfortunately, I couldn't find any information about a song"], "742": ["I couldn't find any information about a song called \""], "743": ["Unfortunately, the provided documents do not mention the League of"], "744": ["I couldn't find any information about a song called \""], "745": ["I couldn't find any information that directly answers the question"], "746": ["The answer is not explicitly mentioned in the provided documents."], "747": ["According to available data, the survival rate of babies born"], "748": ["Unfortunately, the provided documents do not mention anything related to"], "749": ["I couldn't find any information on \"The Walking Dead"], "750": ["Unfortunately, I couldn't find any information on the specific"], "751": ["I couldn't find any information about a character named \""], "752": ["Unfortunately, I couldn't find any information about a song"], "753": ["I couldn't find any relevant information in the provided documents"], "754": ["I couldn't find any information about a \"Peak District"], "755": ["Mucous epithelium"], "756": ["The answer is: 2002"], "757": ["The phrase \"manifest destiny\" was coined by John O"], "758": ["Not found"], "759": ["Unfortunately, the provided documents don't mention any information about"], "760": ["Unfortunately, I couldn't find any information about the first"], "761": ["I couldn't find any information about a person using a"], "762": ["No specific information found regarding the US celebrating St. Patrick"], "763": ["I couldn't find any information that matches the title \""], "764": ["Unfortunately, I couldn't find any information on \"The"], "765": ["I couldn't find any information on a song with the"], "766": ["Novak Djokovic"], "767": ["The first film made in America was \"Roundhay Garden"], "768": ["About 55%"], "769": ["Unfortunately, the provided documents don't seem to be relevant"], "770": ["Unfortunately, the provided documents do not seem to have any"], "771": ["I couldn't find any information on \"Land of the"], "772": ["Bobby"], "773": ["There is no information available in the provided documents about a"], "774": ["I couldn't find any information about Robert Bland from"], "775": ["Unfortunately, I couldn't find any information on a hym"], "776": ["Wharton, TX is approximately 65 miles southwest of"], "777": ["I couldn't find any information on Pakistan winning an Olympic"], "778": ["I couldn't find any information on the Labour Party coming"], "779": ["Unfortunately, the provided documents do not mention the song \""], "780": ["The testes."], "781": ["I couldn't find any information about \"Bring It On"], "782": ["Unfortunately, none of the provided documents mention the introduction of"], "783": ["There is no information available about a Christian monastery founder among"], "784": ["Unfortunately, I couldn't find any information about a song"], "785": ["I couldn't find any information on a TV show called"], "786": ["Androgens"], "787": ["Ocular lens"], "788": ["Unfortunately, the provided documents do not mention the Canadian Charter"], "789": ["I couldn't find any information on a character named \""], "790": ["The International Red Cross was established in 1863 by"], "791": ["I couldn't find any information about a mudslide in"], "792": ["I couldn't find any information about Alfalfa in the"], "793": ["I couldn't find any information about the European Rugby Cup"], "794": ["The Cat in the Hat was written in 1957"], "795": ["No information is found on the number of participants in the"], "796": ["The World Health Organization (WHO) pain ladder consists of"], "797": ["The Boston Tea Party led to the imposition of the Co"], "798": ["The answer is not explicitly stated in the provided documents."], "799": ["In the US, members of Congress are chosen through elections"], "800": ["Unfortunately, I couldn't find any information about a person"], "801": ["I couldn't find any information about a film titled \""], "802": ["I couldn't find any information on who voices Linda's"], "803": ["I couldn't find any information on a song titled \""], "804": ["I couldn't find any information about \"Kung Fu"], "805": ["I couldn't find any information about Smokey the"], "806": ["The question does not match the given documents."], "807": ["Sorry, no information about the theme song from \"Only F"], "808": ["I couldn't find any information on the person holding the"], "809": ["I couldn't find any information on the number of di"], "810": ["Typically around 1-50 employees."], "811": ["It's unclear where the Hemlock Woolly Adel"], "812": ["I couldn't find any information about football on New Year"], "813": ["The creation of the Roman Senate was based on the concept"], "814": ["I couldn't find any information about a character named Harry"], "815": ["There is no information about a person serving as a supreme allied"], "816": ["The answer is Cher."], "817": ["Unfortunately, I couldn't find any information about a movie"], "818": ["Unfortunately, I couldn't find any information about the Methodist"], "819": ["1962"], "820": ["I couldn't find any information about a \"planning"], "821": ["I couldn't find any information on who plays Fat Rh"], "822": ["Zach Galifianakis does not appear to be"], "823": ["I couldn't find any information about the airing schedule for"], "824": ["The first football World Cup was organised in 1930"], "825": ["Unfortunately, I couldn't find any information on a movie"], "826": ["Lorraine Toussaint"], "827": ["The correct answer is: The parliament."], "828": ["I couldn't find any information about the Kansas City Chiefs"], "829": ["The South Carolina Gamecocks won the 2017"], "830": ["Unfortunately, I couldn't find any information about chests of"], "831": ["Walter Conway"], "832": ["A document management system."], "833": ["The Great Wall of China was constructed in multiple stages over"], "834": ["Mikvah"], "835": ["I couldn't find any information on a song or movie"], "836": ["I couldn't find any information on a person with the"], "837": ["Unfortunately, the provided documents don't mention anything about t"], "838": ["1 foot is equal to 0.3048 metres"], "839": ["I couldn't find any information on when capital gains tax"], "840": ["USPTO (United States Patent and Trademark Office"], "841": ["The cell wall"], "842": ["Leonard Cohen"], "843": ["Unfortunately, I couldn't find any information about a \""], "844": ["Not found"], "845": ["I couldn't find any information about \"Lost in Space"], "846": ["I couldn't find any information about the \"mad h"], "847": ["Randy Jackson, Paula Abdul, and Simon Cowell"], "848": ["The Post is about a cover-up in the US Postal"], "849": ["I couldn't find any information about a person who wrote"], "850": ["The national flag of Venezuela is hoisted on January "], "851": ["Coughing up white stuff from the throat can be"], "852": ["I couldn't find any information on a \"Black Knight"], "853": ["Missouri is in the Midwestern United States"], "854": ["A governor can declare a state of emergency in response to"], "855": ["I couldn't find any information about James Nesbitt"], "856": ["I couldn't find any information on the specific song \""], "857": ["I couldn't find any information about a person named Tracy"], "858": ["I couldn't find any information about England reaching a quarter"], "859": ["Unfortunately, I couldn't find any information about a \""], "860": ["I couldn't find any information on the 2017"], "861": ["Lipids are packaged in chylomicrons in"], "862": ["I couldn't find any information on \"shurpn"], "863": ["I couldn't find any information about a character named Paige"], "864": ["The answer is the government."], "865": ["Veronica Mars ends up with Logan Echolls."], "866": ["I couldn't find any information in the provided documents that"], "867": ["The answer is Jawaharlal Nehru."], "868": ["I couldn't find any information about Nigeria launching a satellite"], "869": ["Village People"], "870": ["Ethyl Eichelberger"], "871": ["I couldn't find any information on the voice of the"], "872": ["There is no information about India winning the most medals in"], "873": ["Babe Ruth"], "874": ["I couldn't find any information about a person composing a"], "875": ["No one."], "876": ["I couldn't find any information about a person named Alex"], "877": ["The Bill of Rights was added to the US Constitution by"], "878": ["I couldn't find any information about Jaime Lannister"], "879": ["ABBA's \"Fernando\" is about the"], "880": ["I couldn't find any information about a specific World Cup"], "881": ["I couldn't find any information about the \"Washington Nationals"], "882": ["I couldn't find any information on a movie or show"], "883": ["I couldn't find any information on the FA Cup quarter"], "884": ["5"], "885": ["According to historical records, the Louisiana Purchase in 180"], "886": ["Unfortunately, there is no information about the Beowulf"], "887": ["Websites, databases, forums, social media, wik"], "888": ["I couldn't find any information about the person who voices"], "889": ["I couldn't find any information about India winning the cricket"], "890": ["A bundle of hay is called a \"haystack\"."], "891": ["I couldn't find any information about a movie or TV"], "892": ["No information about the Declaration of Independence is available in the"], "893": ["The US currency left the gold standard in 1971"], "894": ["I couldn't find any information about McCarran Blvd"], "895": ["GI stands for Government Issue."], "896": ["I couldn't find any information in the provided documents about"], "897": ["I couldn't find any information about someone singing \"Charlie"], "898": ["The minister of higher education and scientific research in Egypt is"], "899": ["I couldn't find any information on the first episode of"], "900": ["The electoral college"], "901": ["Unfortunately, none of the provided documents seem to mention the"], "902": ["Linus Torvalds"], "903": ["I couldn't find any information about a person ranked number"], "904": ["I couldn't find any information on a person associated with"], "905": ["Negative symptoms, such as apathy, lack of emotion"], "906": ["The Isle of Man TT is based on the Isle of Man"], "907": ["I couldn't find any information on the 4th"], "908": ["Unfortunately, I couldn't find any information on a person"], "909": ["Unfortunately, I couldn't find any information about a character"], "910": ["\"What is 60 seconds?\""], "911": ["Neither, the \"Man-Eaters of Tsavo\""], "912": ["According to available information, the song \"A Little Help"], "913": ["Ralph Fiennes"], "914": ["The programming language did not have a specific title in the"], "915": ["I couldn't find any information about a movie called \"Return"], "916": ["Tommy Roe"], "917": ["Unfortunately, I couldn't find any information about a song"], "918": ["I couldn't find any information about South Africa winning the"], "919": ["Unfortunately, I couldn't find any information about the current"], "920": ["According to the Book of Mormon's official website, it"], "921": ["Unfortunately, I couldn't find any information on \"Bay"], "922": ["I couldn't find any information about the score for Blade"], "923": ["Tobacco"], "924": ["I couldn't find any information on a song called \""], "925": ["I couldn't find any information about \"Hardy Boy"], "926": ["The United States purchased the Louisiana Territory in 1803"], "927": ["The Church of England allowed female bishops in 2015"], "928": ["They inherit it."], "929": ["I couldn't find any information about Galway winning an"], "930": ["I couldn't find any information on \"Elvira"], "931": ["I couldn't find any information about a governor election in"], "932": ["Unfortunately, I couldn't find any information about the specific"], "933": ["I couldn't find any information about the question \"who"], "934": ["The muscles of facial expression are derived from the first ph"], "935": ["I couldn't find any information about a person or entity"], "936": ["There is no direct mention of the Seven Commandments in"], "937": ["Unfortunately, I couldn't find any information about a song"], "938": ["Typically, a studio apartment is around 400-"], "939": ["There is no mention of the song \"Climb"], "940": ["There is no direct connection between the provided documents and the"], "941": ["Elmo"], "942": ["I couldn't find any information about an actress portraying Wonder"], "943": ["I couldn't find any information about \"telltale's"], "944": ["Unfortunately, I couldn't find any information about Arthur Pend"], "945": ["Unfortunately, I couldn't find any information about an \""], "946": ["The Stamp Act was repealed on March 18, "], "947": ["The answer is Scheme."], "948": ["Unfortunately, I couldn't find any information about a person"], "949": ["Sic semper tyrannis"], "950": ["Unfortunately, I couldn't find any information on a song"], "951": ["Marine"], "952": ["I couldn't find any information about a specific game in"], "953": ["I couldn't find any information on a person named Alice"], "954": ["Unfortunately, the provided documents do not mention what the Romans used"], "955": ["I couldn't find any information on \"The Lion and"], "956": ["The wheel in the middle is for exercise, typically a"], "957": ["The Mindy Project moved to Hulu in 2015"], "958": ["I couldn't find any information about a \"thora"], "959": ["Unfortunately, the provided documents do not mention David's parents"], "960": ["I couldn't find any information on a 1962"], "961": ["The answer is the continental rise."], "962": ["The hottest temperature ever recorded on Earth was 56."], "963": ["I couldn't find any information on the specific duration of"], "964": ["I couldn't find any information about a TV show called"], "965": ["I couldn't find any information about a song titled \""], "966": ["I couldn't find any information on the last championship won"], "967": ["I couldn't find any information about the theme song of"], "968": ["Unfortunately, I couldn't find any information about a specific"], "969": ["Sasha Velour"], "970": ["I couldn't find any information on the last year Ford"], "971": ["I couldn't find any information about a character named James"], "972": ["I couldn't find any information about a specific team winning"], "973": ["I couldn't find any information on who plays the role"], "974": ["The answer is: Everybody Wants to Rule the World is"], "975": ["The three major types of joints in the human body are"], "976": ["Mantis"], "977": ["Unfortunately, I couldn't find any information about a character"], "978": ["The question doesn't mention any of the provided documents,"], "979": ["Unfortunately, the provided documents do not mention the establishment of"], "980": ["The Yankees last won the World Series in 2009"], "981": ["Groups."], "982": ["Medicare Part A."], "983": ["The planet Jupiter is located in the solar system, specifically"], "984": ["I couldn't find any information about the song \"Spl"], "985": ["I couldn't find any Marvel movie in the provided documents"], "986": ["University of North Carolina"], "987": ["The first cell to migrate to an injured area is an"], "988": ["I couldn't find any information about a person named Doc"], "989": ["May 30, 1967"], "990": ["The New Testament is written in Koine Greek."], "991": ["Unfortunately, I couldn't find any information about a sitcom"], "992": ["The Ottoman Empire took over Greece in 1453."], "993": ["I couldn't find any information about a character named \""], "994": ["The song \"Fade to Black\" by Metallica is"], "995": ["I couldn't find any information about the CEO of T"], "996": ["Based on available data, The Beatles have sold the most"], "997": ["I couldn't find any information on \"A Course in"], "998": ["I couldn't find any information about a \"Battle of"], "999": ["I couldn't find any information about \"hanuman ch"]}