{"0": ["Judith Keppel", "Judith Keppel", "Judith Keppel", "Judith Keppel", "Judith Keppel"], "1": ["George W. Bush.", "George W. Bush", "Katherine Harris", "Katherine Harris.", "Bill McBride"], "2": ["Kris Kristofferson", "Kris Kristofferson.", "Kris Kristofferson", "Kris Kristofferson.", "Kris Kristofferson"], "3": ["1904", "1904", "1904", "1904", "1904"], "4": ["2004", "2004", "2004", "2004", "2004"], "5": ["Denzil Ibbetson", "Denzil Ibbetson.", "Denzil Ibbetson.", "Denzil Ibbetson", "Denzil Ibbetson"], "6": ["Regeneration", "Regeneration", "Regeneration", "Wound healing", "Regeneration"], "7": ["Four.", "4", "Nine.", "Four.", "Nine"], "8": ["Exhibition and tourist attraction.", "exhibition and observation.", "exhibition and tourism.", "Tourism", "Exhibition and Tourist Attraction."], "9": ["1775", "1775", "1775", "1775", "April 19, 1775"], "10": ["1830", "1830", "1825", "1830", "1825"], "11": ["According to Document[12](Title: Year zero", "The Hindu-Arabic numeral system, developed in", "0 was first used in mathematical operations in the ", "According to Document[12](Title: Year zero", "In mathematical operations, zero was first used in the"], "12": ["1666", "1666.", "1666", "1666", "1666."], "13": ["Unfortunately, I couldn't find any information about the", "I couldn't find any information on the CEO of", "Not found.", "Not available.", "Unfortunately, I couldn't find any information about the"], "14": ["The Winnie-the-Pooh books were written", "The Winnie-the-Pooh books were written", "The Winnie-the-Pooh books were written", "The Winnie-the-Pooh books were written", "The Winnie-the-Pooh books were written"], "15": ["2017", "2017", "2017", "The Adelaide Crows last appeared in the 201", "2018"], "16": ["E.G. Daily", "E.G. Daily", "E.G. Daily", "E.G. Daily", "E.G. Daily"], "17": ["The Kingston Trio.", "The Kingston Trio", "The Kingston Trio", "The Kingston Trio.", "The Kingston Trio."], "18": ["The first Thursday Night Football game was played by the", "The 2006 New York Giants played the first", "The 1970 Baltimore Colts played the first NFL", "The 1970 Dallas Cowboys played the first NFL", "The first NFL Thursday Night Football game was played between"], "19": ["The Big Bang Theory (season 11) has", "The Big Bang Theory (season 11) has", "The Big Bang Theory (season 11) has", "Document[16](Title: List of The Big", "The Big Bang Theory (season 11) has"], "20": ["Various regions, including West Africa, East Africa,", "Many areas of Africa were involved in colonization, including", "Various regions, including West Africa, East Africa,", "Many areas of Africa were involved in colonization, including", "Scramble for Africa, West, East,"], "21": ["The show \"Dancing on Ice\" typically airs", "The series typically airs on ITV in the UK.", "The show \"Dancing on Ice\" typically airs", "Typically airs on ITV in the UK.", "The TV series \"Dancing on Ice\" typically"], "22": ["He is talking about his wife.", "He is talking about his daughter.", "The song \"I Drive Your Truck\" by Lee", "Himself", "The person he's talking about is likely a romantic"], "23": ["Deserts, like the Great Victoria Desert, are", "Deserts are home to various small mammals, including", "Deserts, including the Great Victoria Desert, are", "Deserts, including the Great Victoria Desert, are", "Deserts, such as the Great Victoria Desert,"], "24": ["The last God of War game, \"God of", "The last game in the series is God of War", "The last main installment in the series is the ", "The 2018 version.", "2018"], "25": ["According to Document[3](Title: Whooping", "The first whole-cell pertussis vaccine was introduced", "The first whole-cell pertussis vaccine was licensed", "In the United States, widespread vaccination for whooping", "According to Document[11], childhood immunizations in"], "26": ["The answer is Domain (16): Eukarya", "Answer: Bacteria", "Answer: Eukarya", "Answer: Archaea or Bacteria", "Eukarya"], "27": ["Little Boy.", "Little Boy", "Little Boy", "Little Boy", "Little Boy"], "28": ["The Maple Leaf Square and Scotiabank Arena", "Maple Leaf Square.", "Maple Leaf Square.", "The Maple Leafs play hockey at the Scotiab", "The Toronto Maple Leafs play hockey at the Scoti"], "29": ["West Siberian Laika", "West Siberian Laika", "West Siberian Laika", "West Siberian Laika", "West Siberian Laika"], "30": ["The 2017 Houston Astros won the American League", "The 2017 Houston Astros won the American League", "The 2017 Houston Astros won the American League", "The Washington Nationals won the American League pennant in", "The 2017 Houston Astros."], "31": ["Kami Rita Sherpa, with 25 summ", "Kami Rita Sherpa", "Kami Rita Sherpa", "Kami Rita Sherpa", "Kami Rita Sherpa"], "32": ["Allan Clarke", "The song \"Picking Up Pebbles and Th", "The Hollies", "The Hollies.", "The Hollies"], "33": ["The answer is: Moringa oleifera", "No answer found in the documents.", "Moringa oleifera", "I couldn't find any information about plants named \"", "Fenugreek"], "34": ["Caleb Landry Jones", "Caleb Landry Jones", "Topher Grace", "Topher Grace", "Caleb Landry Jones"], "35": ["Dhyan Chand won India's first two Olympic", "Dhyan Chand won India's first Olympic gold", "Dhyan Chand won India's first Olympic gold", "Dhyan Chand won the first Olympic gold medal", "Dhyan Chand won the first Olympic medal for"], "36": ["Wheat, Maize (corn), and other", "wheat maize corn", "The main crops grown in the United States include maize", "Corn, wheat, and soybeans.", "maize and wheat"], "37": ["The Age of New Media began around 1990", "1991", "1990s", "The \"Age of New Media\" began in the", "1991"], "38": ["1953", "1953", "1953", "1953", "1953"], "39": ["2019.", "2011-12.", "2019", "2011", "2019"], "40": ["Eric van der Woodsen ends up with Jenny Humph", "Eric van der Woodsen ends up with Serena van", "Van der Woodsen.", "XOXO, Blair", "Eric van der Woodsen."], "41": ["1965", "1965", "1971", "1965", "1971"], "42": ["According to Document 15, Major League Baseball ro", "According to Major League Baseball rosters (Document ", "According to Document[15](Title: Major League", "According to Document[15](Title: Major League", "According to Document[15](Title: Major League"], "43": ["Josh Peck", "Drake Bell", "Josh Peck", "Jonathan Goldstein", "Josh Peck"], "44": ["Liam Cunningham", "Finn Jones", "Finn Jones", "Finn Jones", "Liam Cunningham"], "45": ["Oxidation, forming rust.", "Anaerobic corrosion.", "Forms rust.", "iron oxidizes to rust", "Iron(II) oxide forms, releasing hydrogen gas"], "46": ["Philippa Lowthorpe", "Linda Bassett", "Bryony Hannah", "Helen George", "Linda Bassett"], "47": ["He painted 3.", "12", "12", "12.", "7"], "48": ["Felix Baumgartner", "Felix Baumgartner", "Felix Baumgartner", "Felix Baumgartner", "Felix Baumgartner"], "49": ["The Lightning Thief.", "The Lightning Thief.", "The Lightning Thief.", "The Lightning Thief", "The Lightning Thief"]}